[
	{
		"FileName": "pbXNet/pbXNet.AssemblyInfo.cs",
		"Entries": [
			{
				"Pattern": "AssemblyVersion\\(\"([0-9]+)\\.([0-9]+)\\.([0-9]+)\\.([0-9*]+)\"\\)"
			},
			{
				"Pattern": "AssemblyFileVersion\\(\"([0-9]+)\\.([0-9]+)\\.([0-9]+)\\.([0-9*]+)\"\\)"
			}
		]
	},
	{
		"FileNames": [
			"pbXNet.Droid/pbXNet.Droid.csproj",
			"pbXNet.iOS/pbXNet.iOS.csproj",
			"pbXNet.macOS/pbXNet.macOS.csproj",
			"pbXNet.UWP/pbXNet.UWP.csproj",
			"pbXNet/pbXNet.Shared.shproj",
		],
		"Entries": [
			{
				"Pattern": "<ReleaseVersion>\\s*([0-9]+)\\.([0-9]+)\\.([0-9]+)\\.([0-9]+)\\s*</ReleaseVersion>"
			}
		]

	},
]